utk_streamer/__init__.py
utk_streamer/convert/__init__.py
utk_streamer/convert/convert.py
utk_streamer/download/__init__.py
utk_streamer/download/download.py
utk_streamer/streamer.py
utk_streamer-0.2.1.dist-info/METADATA
utk_streamer-0.2.1.dist-info/WHEEL
utk_streamer-0.2.1.dist-info/entry_points.txt
utk_streamer-0.2.1.dist-info/RECORD
