Metadata-Version: 2.1
Name: utk_streamer
Version: 0.2.1
Summary: Simple utility to download multiple files from a sheet at once
Author: Mark Baggett
Author-email: mbagget1@utk.edu
Requires-Python: >=3.8,<4.0
Classifier: Programming Language :: Python :: 3
Classifier: Programming Language :: Python :: 3.8
Classifier: Programming Language :: Python :: 3.9
Classifier: Programming Language :: Python :: 3.10
Classifier: Programming Language :: Python :: 3.11
Classifier: Programming Language :: Python :: 3.12
Requires-Dist: click (>=8.1.7,<9.0.0)
Requires-Dist: lxml (>=5.2.2,<6.0.0)
Requires-Dist: requests (>=2.32.2,<3.0.0)
Requires-Dist: tqdm (>=4.66.4,<5.0.0)
